pyvipr/__init__.py
pyvipr/_version.py
pyvipr/bipartite_projection.py
pyvipr/model_simresult_to_json.py
pyvipr/package-lock.json
pyvipr/util.py
pyvipr/util_networkx.py
pyvipr/viz.py
pyvipr/examples_models/__init__.py
pyvipr/examples_models/albeck_modules.py
pyvipr/examples_models/bid_compartments.py
pyvipr/examples_models/double_enzymatic_sbml.xml
pyvipr/examples_models/earm_incorrect.py
pyvipr/examples_models/lopez_embedded.py
pyvipr/examples_models/lopez_modules.py
pyvipr/examples_models/mm_two_paths_model.py
pyvipr/examples_models/organelle_transport.bngl
pyvipr/examples_models/organelle_transport.py
pyvipr/examples_models/shared.py
pyvipr/examples_models/ensemble_1_bng/ensemble_1.bngl
pyvipr/examples_models/ensemble_1_bng/ensemble_1_opts.txt
pyvipr/network_viz/__init__.py
pyvipr/network_viz/network_viz.py
pyvipr/network_viz/views.py
pyvipr/pysb_viz/__init__.py
pyvipr/pysb_viz/dynamic_viz.py
pyvipr/pysb_viz/static_viz.py
pyvipr/pysb_viz/views.py
pyvipr/static/extension.js
pyvipr/static/index.js
pyvipr/static/index.js.LICENSE.txt
pyvipr/static/index.js.map
pyvipr/staticlab/README.md
pyvipr/staticlab/package.json
pyvipr/staticlab/static/142.46114563434fa17e1341.js
pyvipr/staticlab/static/142.d1260c428e39ebae8def.js
pyvipr/staticlab/static/143.f11a2433740b8bbe55e6.js
pyvipr/staticlab/static/172.fb9e62364992e8ef2ad9.js
pyvipr/staticlab/static/187.9f64e19bfaa3de00cd17.js
pyvipr/staticlab/static/261.a9f0fda99f6915756664.js
pyvipr/staticlab/static/486.c9ecbbde2292967a2e67.js
pyvipr/staticlab/static/486.c9ecbbde2292967a2e67.js.LICENSE.txt
pyvipr/staticlab/static/504.2f138964464ec46cabfa.js
pyvipr/staticlab/static/526.541decf99aa6961a98b5.js
pyvipr/staticlab/static/526.541decf99aa6961a98b5.js.LICENSE.txt
pyvipr/staticlab/static/548.c8a9f5e70fc39dff5c0b.js
pyvipr/staticlab/static/568.9c1804903f6b5697e24b.js
pyvipr/staticlab/static/568.e509d56a970619cb6312.js
pyvipr/staticlab/static/578.4110b3ecea709bc7a495.js
pyvipr/staticlab/static/58.5c474e2176e381f75172.js
pyvipr-1.0.7.dist-info/LICENSE
pyvipr-1.0.7.dist-info/METADATA
pyvipr-1.0.7.dist-info/WHEEL
pyvipr-1.0.7.dist-info/top_level.txt
pyvipr-1.0.7.dist-info/RECORD
