Metadata-Version: 2.1
Name: pyvipr
Version: 1.0.7
Summary: Widget to visualize PySB models in Jupyter Notebook
Home-page: https://github.com/LoLab-VU/pyvipr
Author: Oscar Ortega
Author-email: oscar.ortega@vanderbilt.edu
License: UNKNOWN
Keywords: ipython,jupyter,widgets,pysb,systems biology,cytoscape,graph,visualization
Platform: UNKNOWN
Classifier: Development Status :: 4 - Beta
Classifier: Framework :: IPython
Classifier: Intended Audience :: Developers
Classifier: Intended Audience :: Science/Research
Classifier: Topic :: Multimedia :: Graphics
Classifier: Programming Language :: Python :: 3
Classifier: Programming Language :: Python :: 3.3
Classifier: Programming Language :: Python :: 3.4
Classifier: Programming Language :: Python :: 3.5
Classifier: Programming Language :: Python :: 3.6
License-File: LICENSE
Requires-Dist: ipywidgets (>=7.0.0)
Requires-Dist: networkx (>=2.2)
Requires-Dist: numpy (>=1.15.4)
Requires-Dist: sympy (>=1.3)
Requires-Dist: matplotlib (>=3.0.2)
Requires-Dist: python-louvain (>=0.13)
